sosecrets_core/py.typed
sosecrets_core/secrets.c
sosecrets_core/secrets.cp310-win_amd64.pyd
sosecrets_core/secrets.pyi
sosecrets_core/secrets.pyx
sosecrets_core-1.0.20.dist-info/LICENSE
sosecrets_core-1.0.20.dist-info/METADATA
sosecrets_core-1.0.20.dist-info/WHEEL
sosecrets_core-1.0.20.dist-info/top_level.txt
sosecrets_core-1.0.20.dist-info/RECORD
