Metadata-Version: 2.1
Name: sosecrets-core
Version: 1.0.20
Summary: Simple Secret Primitive for Python
Home-page: http://github.com/jymchng/sosecrets-core
Author: Jim Chng
Author-email: jimchng@outlook.com
License: MIT
Keywords: secrets security secrets-management
Classifier: Programming Language :: Python
Classifier: Programming Language :: Python :: 3.7
Classifier: Programming Language :: Python :: 3.8
Classifier: Programming Language :: Python :: 3.9
Classifier: Programming Language :: Python :: 3.10
Classifier: Programming Language :: Python :: 3.11
Classifier: Programming Language :: Python :: Implementation :: CPython
Classifier: Programming Language :: Cython
Classifier: Operating System :: POSIX :: Linux
Classifier: Operating System :: Microsoft :: Windows
License-File: LICENSE
